json_comp/__init__.py
json_comp/comp.py
json_compare/__init__.py
json_compare/comp.py
json_comp-1.dist-info/LICENSE.txt
json_comp-1.dist-info/METADATA
json_comp-1.dist-info/WHEEL
json_comp-1.dist-info/top_level.txt
json_comp-1.dist-info/RECORD
